nate/__init__.py
nate/py.typed
nate/tags.py
nate-0.0.7.dist-info/LICENSE
nate-0.0.7.dist-info/METADATA
nate-0.0.7.dist-info/WHEEL
nate-0.0.7.dist-info/top_level.txt
nate-0.0.7.dist-info/RECORD
