Metadata-Version: 2.1
Name: nate
Version: 0.0.7
Summary: Make generating HTML fun.
Home-page: https://github.com/alexanderGugel/nate
Author: Alexander Gugel
Author-email: alexander.gugel@gmail.com
License: UNKNOWN
Platform: UNKNOWN
Classifier: Programming Language :: Python :: 3
Classifier: License :: OSI Approved :: MIT License
Classifier: Operating System :: OS Independent
Requires-Python: >=3.7
